customidenticon/__init__.py
customidenticon-0.1.5.dist-info/LICENSE
customidenticon-0.1.5.dist-info/METADATA
customidenticon-0.1.5.dist-info/WHEEL
customidenticon-0.1.5.dist-info/top_level.txt
customidenticon-0.1.5.dist-info/RECORD
