Metadata-Version: 2.1
Name: customidenticon
Version: 0.1.5
Summary: Python3 library for generate a variety of identicons
Home-page: https://github.com/lexserest/customidenticon
Author: LexSerest
Author-email: lexserest@gmail.com
Maintainer: LexSerest
Maintainer-email: lexserest@gmail.com
License: MIT
Keywords: identicon image avatar profile github custom customidenticon
Platform: UNKNOWN
Requires-Dist: pillow
